README.md
setup.cfg
setup.py
microcosm_dynamodb/__init__.py
microcosm_dynamodb/createall.py
microcosm_dynamodb/errors.py
microcosm_dynamodb/factories.py
microcosm_dynamodb/health.py
microcosm_dynamodb/identifiers.py
microcosm_dynamodb/mockengine.py
microcosm_dynamodb/models.py
microcosm_dynamodb/operations.py
microcosm_dynamodb/store.py
microcosm_dynamodb.egg-info/PKG-INFO
microcosm_dynamodb.egg-info/SOURCES.txt
microcosm_dynamodb.egg-info/dependency_links.txt
microcosm_dynamodb.egg-info/entry_points.txt
microcosm_dynamodb.egg-info/not-zip-safe
microcosm_dynamodb.egg-info/requires.txt
microcosm_dynamodb.egg-info/top_level.txt
microcosm_dynamodb/loaders/__init__.py
microcosm_dynamodb/loaders/base.py
microcosm_dynamodb/loaders/conventions.py
microcosm_dynamodb/loaders/encrypted.py
microcosm_dynamodb/loaders/operations.py
microcosm_dynamodb/loaders/plaintext.py