Metadata-Version: 1.1
Name: microcosm-dynamodb
Version: 1.0.0
Summary: Opinionated persistence with DynamoDB
Home-page: https://github.com/globality-corp/microcosm-dynamodb
Author: Globality Engineering
Author-email: engineering@globality.com
License: Apache v2.0 License
Download-URL: http://pypi.python.org/pypi/microcosm-dynamodb
Keywords: microcosm,dynamodb
Platform: Linux
Classifier: Intended Audience :: Developers
